{
  "hash": "d0cb5a45150ee7af7c11194f34919894",
  "result": {
    "markdown": "---\ntitle: \"荣格自传\"\nsubtitle: \"回忆·梦·思考\"\ndate: \"2023-12-29\"\ndate-modified: \"2024-01-27\"\nimage: \"cover.jpg\"\ncategories: \n  - Psychology\n---\n\n\n\n\n::: {.callout-note title='Progress'}\nLearning Progress: 9%.\n\n<!-- 读后感：[读《管理行为》](https://shitao5.org/posts/glxw/)。 -->\n:::\n\n::: {.callout-tip title=\"Learning Source\"}\n- <https://book.douban.com/subject/25793666/>\n:::\n\n# 译序 {-}\n\n- 在人的精神或人格中，基本或基础性的东西乃是伊德所代表的潜意识。无论自我还是超自我均派生自它。所以潜意识是第一性的，意识是第二性的，每一种心理过程最初都是潜意识的，只是经过一定条件和一定时间，才发展成为意识的。但是潜意识的心理过程并不一定都能变成有意识的心理过程。而有意识的心理现象往往是虚假的、象征性的，其真正面目、动机、目的只有通过精神分析，求之于潜意识这个特殊的精神领域。弗洛伊德的伟大贡献之一，就在于把心理学的研究范围扩大到了潜意识的领域。\n\n- 荣格认为，人的心理是通过进化而预先确定了的。个人因而同往昔联结到了一起，不仅与自己童年的往昔，更重要的是还与种族的往昔相联结，甚至还与有机界的整个漫长的进化过程相联结。这一往昔，并不只是个人的潜意识，而主要是“集体的”潜意识。集体潜意识的发现，是荣格的卓越成就，是心理学史上的一座里程碑。\n\n- 弗洛伊德所发现的潜意识，实际上只是“个人潜意识”，是潜意识中的一部分，潜意识中的“集体潜意识”，才是一个包容更广的天地。\n\n- 集体潜意识的发现扩大了人们对人的精神与心理的了解。集体潜意识与个人潜意识一样，也是一个贮存所，它所贮存的是大量初始的或本源性的潜在意象。集体潜意识是一种心灵虚像，它只有与相对应的客观事物相结合，才能成为意识中的实在。它犹如一个公式，是一种“没有内容的形式”，虽然是虚的，但一与代入的具体内容相结合，就会在实际中发生作用。因此后天习得的经验越多，潜在于潜意识中的虚像得以显现的机会便越多。教育与学习上的机会与环境越丰富，集体潜意识的各方面便可以变得个性化并成为自觉的意识。\n\n# 绪论 {-}\n\n- 他那些主观性的表述只有对于有相似体验的人来说才是可以接受的——或用另一种方式来说，只对在其精神里上帝的形象带有着同样的或相似的特征的那些人才是可以接受的。\n\n- 这本‘自传’是我一生的记载，是从我据我的科学研究中所获得的知识来观察的。这二者是一回事，因此这本书对那些不懂得或不理解我的科学观点的人们提出了很高要求。我的一生在某种意义上是我所写的一切的结晶而不是相反。我存在的方式及我写作的方式是一个整体。我的所有观念及我所有的努力就是我本人的写照。因此，这本‘自传’只是‘我’这个字上的一‘点’就是了。”\n\n- 荣格是不断地以新的及不同的方式来定义他的概念的，因为他感到，作出终极性定义是不可能的。他认为明智的做法是让总是附于精神现实的各种无法解释的要素像谜或神秘的东西那样原封不动地保留着为好。\n\n# 序言 {-}\n\n- 到了最后，在我一生中唯一值得讲述的事件，是那永远不会毁灭的世界闯进了这个转变性的世界的那些事件。这就是何以我主要谈些内心体验的原因，这其中便包括了我的各种梦及幻觉。\n\n- 我们是一种我们所无法控制的或只是部分地有能力加以引导的精神过程。因此，对于我们自己或我们的生命，我们无法拥有任何终极性的判断。我们要是拥有，那我们就会无所不知了——但这最多只不过是一种自以为是的借口而已。在心底处，我们是决不会知道这一切到底是怎么回事的。一个人的生命的故事始于某处，始于某个我们碰巧记得的特定的某一点；而且甚至就在那时，它就已经是高度复杂的了。我们并不知道生命的结果将会是什么。因此，这个故事是没有开头的，而其结局也就只能含含糊糊地加以暗示而已。\n\n# 童年\n\n- 这一类姑娘后来成了我潜意识中异性人格化的一个组成部分。她所传达的那种既生疏又始终为人所认识的感觉，是后来在我心中象征女性本质的那个形象的一种特征。\n\n- 对于这些行为的意义，或者究竟该怎样解释它们，我毫不在意。我满足于有一种安全感，满足于占有某种别人不知道而又无法获得的东西。这是一种永远不能背叛的秘密，因为我生命的安全由它掌握。为什么如此，我没有问过自己。事情就是这样。\n\n\n\n\n\n\n\n\n\n\n\n\n\n\n\n\n\n\n\n\n\n\n\n\n\n\n\n\n\n\n\n\n\n\n\n\n\n\n\n\n\n\n\n\n\n\n\n\n\n\n\n\n\n\n\n\n\n\n",
    "supporting": [
      "index_files"
    ],
    "filters": [
      "rmarkdown/pagebreak.lua"
    ],
    "includes": {},
    "engineDependencies": {},
    "preserve": {},
    "postProcess": true
  }
}